aliyun_table/__init__.py
aliyun_table/my_logger.py
aliyun_table-0.1.2.dist-info/LICENSE.txt
aliyun_table-0.1.2.dist-info/METADATA
aliyun_table-0.1.2.dist-info/WHEEL
aliyun_table-0.1.2.dist-info/top_level.txt
aliyun_table-0.1.2.dist-info/RECORD
