Metadata-Version: 2.1
Name: aliyun-table
Version: 0.1.2
Summary: Aliyun Tablestore Operations, make aliyun tablestore more simple.
Home-page: https://github.com/RunningIkkyu/aliyun-table
Author: Lane
Author-email: GeekerLane@gmail.com
License: UNKNOWN
Platform: UNKNOWN
Classifier: Programming Language :: Python :: 3
Classifier: License :: OSI Approved :: MIT License
Classifier: Operating System :: OS Independent
Requires-Python: >=3.6
Requires-Dist: pprint
Requires-Dist: tablestore
Requires-Dist: prettytable
